dependency_algorithm/__init__.py
dependency_algorithm/dependency_algorithm.py
dependency_algorithm/version.py
dependency_algorithm-0.1.dist-info/LICENSE
dependency_algorithm-0.1.dist-info/METADATA
dependency_algorithm-0.1.dist-info/WHEEL
dependency_algorithm-0.1.dist-info/top_level.txt
dependency_algorithm-0.1.dist-info/RECORD
