Metadata-Version: 2.1
Name: dependency-algorithm
Version: 0.1
Summary: Automatically identify and order dependencies so that they resolve correctly
Home-page: https://github.com/jakesherman/dependency_algorithm
Author: Jake Sherman
Author-email: jake@jakesherman.com
License: MIT License
Download-URL: https://github.com/jakesherman/dependency_algorithm/archive/v0.1.tar.gz
Keywords: dependency,dependencies,dependency management
Platform: UNKNOWN
Requires-Python: >=3.7
Requires-Dist: pytest (>=3.1.0)
